src/tbotapi/__init__.py
src/tbotapi/exceptions.py
src/tbotapi/logger.py
src/tbotapi/telegram.py
src/tbotapi/bot/__init__.py
src/tbotapi/bot/bot.py
src/tbotapi/bot/methods.py
src/tbotapi/bot/session.py
src/tbotapi/enums/__init__.py
src/tbotapi/enums/bot_command_scope_type.py
src/tbotapi/enums/chat_action.py
src/tbotapi/enums/chat_member_status.py
src/tbotapi/enums/chat_type.py
src/tbotapi/enums/content_type.py
src/tbotapi/enums/dice_emoji.py
src/tbotapi/enums/inline_query_result_type.py
src/tbotapi/enums/input_media_type.py
src/tbotapi/enums/mask_position_point.py
src/tbotapi/enums/menu_button_type.py
src/tbotapi/enums/message_entity_type.py
src/tbotapi/enums/parse_mode.py
src/tbotapi/enums/poll_type.py
src/tbotapi/enums/sticker_type.py
src/tbotapi/enums/topic_icon_color.py
src/tbotapi/enums/update_type.py
src/tbotapi/methods/__init__.py
src/tbotapi/methods/add_sticker_to_set.py
src/tbotapi/methods/answer_callback_query.py
src/tbotapi/methods/answer_inline_query.py
src/tbotapi/methods/answer_pre_checkout_query.py
src/tbotapi/methods/answer_shipping_query.py
src/tbotapi/methods/answer_web_app_query.py
src/tbotapi/methods/approve_chat_join_request.py
src/tbotapi/methods/ban_chat_member.py
src/tbotapi/methods/ban_chat_sender_chat.py
src/tbotapi/methods/base.py
src/tbotapi/methods/close.py
src/tbotapi/methods/close_forum_topic.py
src/tbotapi/methods/close_general_forum_topic.py
src/tbotapi/methods/copy_message.py
src/tbotapi/methods/create_chat_invite_link.py
src/tbotapi/methods/create_forum_topic.py
src/tbotapi/methods/create_invoice_link.py
src/tbotapi/methods/create_new_sticker_set.py
src/tbotapi/methods/decline_chat_join_request.py
src/tbotapi/methods/delete_chat_photo.py
src/tbotapi/methods/delete_chat_sticker_set.py
src/tbotapi/methods/delete_forum_topic.py
src/tbotapi/methods/delete_message.py
src/tbotapi/methods/delete_my_commands.py
src/tbotapi/methods/delete_sticker_from_set.py
src/tbotapi/methods/delete_webhook.py
src/tbotapi/methods/edit_chat_invite_link.py
t_bot_api-1.0.1.dist-info/METADATA
t_bot_api-1.0.1.dist-info/WHEEL
t_bot_api-1.0.1.dist-info/RECORD
